smallssd/__init__.py
smallssd/config.py
smallssd/data.py
smallssd/keys.py
smallssd/utils.py
smallssd-0.0.5.dist-info/LICENSE
smallssd-0.0.5.dist-info/METADATA
smallssd-0.0.5.dist-info/WHEEL
smallssd-0.0.5.dist-info/top_level.txt
smallssd-0.0.5.dist-info/RECORD
