Metadata-Version: 2.1
Name: smallssd
Version: 0.0.5
Summary: Open source agricultural data
Home-page: https://github.com/smallrobotcompany/smallssd
Author: Gabriel Tseng
Author-email: gabrieltseng95@gmail.com
Classifier: Programming Language :: Python :: 3
Classifier: License :: Other/Proprietary License
Classifier: Operating System :: OS Independent
Requires-Python: >=3.8
License-File: LICENSE
Requires-Dist: protobuf (==3.20.1)
Requires-Dist: tqdm (>=4.61.1)
Requires-Dist: torch (>=1.11.0)
Requires-Dist: torchvision (>=0.12.0)
Requires-Dist: pillow (>=9.1.0)
